emp_agents/__init__.py
emp_agents/exceptions.py
emp_agents/logger.py
emp_agents/py.typed
emp_agents/agents/__init__.py
emp_agents/agents/base.py
emp_agents/agents/history.py
emp_agents/agents/persistentagent.py
emp_agents/agents/planner.py
emp_agents/agents/skills.py
emp_agents/config/__init__.py
emp_agents/config/agent_config.py
emp_agents/implicits/__init__.py
emp_agents/implicits/manager.py
emp_agents/implicits/models/__init__.py
emp_agents/middleware/__init__.py
emp_agents/middleware/rag/__init__.py
emp_agents/middleware/rag/_type.py
emp_agents/middleware/rag/ragie.py
emp_agents/models/__init__.py
emp_agents/models/middleware.py
emp_agents/models/provider.py
emp_agents/models/protocol/__init__.py
emp_agents/models/protocol/decorators.py
emp_agents/models/protocol/registry.py
emp_agents/models/protocol/skill_set.py
emp_agents/models/shared/__init__.py
emp_agents/models/shared/example.py
emp_agents/models/shared/message.py
emp_agents/models/shared/request.py
emp_agents/models/shared/tools.py
emp_agents/providers/__init__.py
emp_agents/providers/standard_request.py
emp_agents/providers/anthropic/__init__.py
emp_agents/providers/anthropic/request.py
emp_agents/providers/anthropic/response.py
emp_agents/providers/anthropic/tool.py
emp_agents/providers/anthropic/types.py
emp_agents/providers/deepseek/__init__.py
emp_agents/providers/deepseek/types.py
emp_agents/providers/grok/__init__.py
emp_agents/providers/grok/request.py
emp_agents/providers/grok/response.py
emp_agents/providers/grok/types.py
emp_agents/providers/openai/__init__.py
emp_agents/providers/openai/request.py
emp_agents/providers/openai/response.py
emp_agents/providers/openai/tool.py
emp_agents/providers/openai/types.py
emp_agents/providers/openrouter/__init__.py
emp_agents/providers/openrouter/types.py
emp_agents/tools/__init__.py
emp_agents/tools/dexscreener/__init__.py
emp_agents/tools/dexscreener/api.py
emp_agents/tools/protocol/__init__.py
emp_agents/tools/protocol/erc20/__init__.py
emp_agents-0.3.3.dist-info/licenses/LICENSE
emp_agents-0.3.3.dist-info/METADATA
emp_agents-0.3.3.dist-info/WHEEL
emp_agents-0.3.3.dist-info/top_level.txt
emp_agents-0.3.3.dist-info/RECORD
