Metadata-Version: 2.4
Name: emp-agents
Version: 0.3.3
Summary: A Python library for building low-code, capable and extensible autonomous agent systems.
Author: Johnny, Rick
License: MIT
Keywords: emp,agents,python
Classifier: Programming Language :: Python :: 3
Classifier: Programming Language :: Python :: 3.10
Classifier: Programming Language :: Python :: 3.11
Classifier: Programming Language :: Python :: 3.12
Classifier: Operating System :: OS Independent
Requires-Python: <4,>=3.10
License-File: LICENSE
Requires-Dist: aiohttp==3.10.5
Requires-Dist: anthropic==0.42.0
Requires-Dist: cryptography==43.0.3
Requires-Dist: eth-rpc-py>=0.1.30
Requires-Dist: eth-typeshed-py
Requires-Dist: fast-depends>=2.4.0
Requires-Dist: httpx>=0.27.2
Requires-Dist: pydantic>=2.9.2
Requires-Dist: tiktoken==0.7.0
Requires-Dist: fast_depends>=2.4.0
Requires-Dist: pyyaml
Requires-Dist: mcp<2.0.0,>=1.6.0
Provides-Extra: tools
Requires-Dist: tweepy>=4.14.0; extra == "tools"
Provides-Extra: test
Requires-Dist: pytest>=7.0.0; extra == "test"
Requires-Dist: pytest-asyncio>=0.23.0; extra == "test"
Provides-Extra: dev
Requires-Dist: jupyter==1.1.1; extra == "dev"
Dynamic: license-file
